README.md
setup.cfg
setup.py
rabpro/__init__.py
rabpro/core.py
rabpro/elev_profile.py
rabpro/merit_utils.py
rabpro/subbasin_stats.py
rabpro/subbasins.py
rabpro/utils.py
rabpro.egg-info/PKG-INFO
rabpro.egg-info/SOURCES.txt
rabpro.egg-info/dependency_links.txt
rabpro.egg-info/requires.txt
rabpro.egg-info/top_level.txt