Metadata-Version: 2.1
Name: rabpro
Version: 0.2.2
Summary: Package to delineate subbasins and compute statistics.
Home-page: https://github.com/jschwenk/rabpro
Author: Example Author
Author-email: author@example.com
License: UNKNOWN
Project-URL: Bug Tracker, https://github.com/jschwenk/rabpro/issues
Platform: UNKNOWN
Classifier: Programming Language :: Python :: 3
Classifier: License :: OSI Approved :: BSD License
Classifier: Operating System :: OS Independent
Requires-Python: >=3.6
